[{"Year":"2020","Value":152134672,"GeoCode":null,"Observation status":"Normal value","Unit multiplier":"Units","UNIT_MEASURE":"Number","SERIES":"Beach litter per square kilometer (Number) [14.1.1]"},{"Year":"2019","Value":179760103,"GeoCode":null,"Observation status":"Normal value","Unit multiplier":"Units","UNIT_MEASURE":"Number","SERIES":"Beach litter per square kilometer (Number) [14.1.1]"},{"Year":"2017","Value":56875108,"GeoCode":null,"Observation status":"Normal value","Unit multiplier":"Units","UNIT_MEASURE":"Number","SERIES":"Beach litter per square kilometer (Number) [14.1.1]"},{"Year":"2016","Value":33579283,"GeoCode":null,"Observation status":"Normal value","Unit multiplier":"Units","UNIT_MEASURE":"Number","SERIES":"Beach litter per square kilometer (Number) [14.1.1]"}]