<?xml version="1.0" ?>
<!--Created with SDMX Converter v7.7.2-->
<message:StructureSpecificData xmlns:ss="http://www.sdmx.org/resources/sdmxml/schemas/v2_1/data/structurespecific" xmlns:footer="http://www.sdmx.org/resources/sdmxml/schemas/v2_1/message/footer" xmlns:ns1="urn:sdmx:org.sdmx.infomodel.datastructure.DataStructure=GSS:SDG(1.2):ObsLevelDim:TIME_PERIOD" xmlns:message="http://www.sdmx.org/resources/sdmxml/schemas/v2_1/message" xmlns:common="http://www.sdmx.org/resources/sdmxml/schemas/v2_1/common" xmlns:xsi="http://www.w3.org/2001/XMLSchema-instance">
  <message:Header>
    <message:ID>IREF1665189293148</message:ID>
    <message:Test>false</message:Test>
    <message:Prepared>2022-10-08T00:34:53Z</message:Prepared>
    <message:Sender id="BIS">
      <message:Contact></message:Contact>
    </message:Sender>
    <message:Structure structureID="GSS_SDG_1_2" namespace="urn:sdmx:org.sdmx.infomodel.datastructure.DataStructure=GSS:SDG(1.2):ObsLevelDim:TIME_PERIOD" dimensionAtObservation="TIME_PERIOD">
      <common:Structure>
        <Ref agencyID="GSS" id="SDG" version="1.2"></Ref>
      </common:Structure>
    </message:Structure>
    <message:DataSetAction>Information</message:DataSetAction>
    <message:DataSetID>SDG</message:DataSetID>
  </message:Header>
  <message:DataSet ss:dataScope="DataStructure" xsi:type="ns1:DataSetType" ss:structureRef="GSS_SDG_1_2" ss:action="Information">
  <Series FREQ="A" REPORTING_TYPE="N" SERIES="_L_GH_140101_01" REF_AREA="GH" SEX="_T" AGE="_T" URBANISATION="_T" INCOME_WEALTH_QUANTILE="_T" EDUCATION_LEV="_T" OCCUPATION="_T" CUST_BREAKDOWN="_T" COMPOSITE_BREAKDOWN="_T" DISABILITY_STATUS="_T" ACTIVITY="_T" PRODUCT="_T" UNIT_MEASURE="KM2">
    <Obs TIME_PERIOD="2020" OBS_VALUE="152134672" OBS_STATUS="A" UNIT_MULT="0" NATURE="_X" TIME_DETAIL="2020" SOURCE_DETAIL="TIDES database"></Obs>
    <Obs TIME_PERIOD="2019" OBS_VALUE="179760103" OBS_STATUS="A" UNIT_MULT="0" NATURE="_X" TIME_DETAIL="2019" SOURCE_DETAIL="TIDES database"></Obs>
    <Obs TIME_PERIOD="2017" OBS_VALUE="56875108" OBS_STATUS="A" UNIT_MULT="0" NATURE="_X" TIME_DETAIL="2017" SOURCE_DETAIL="TIDES database"></Obs>
    <Obs TIME_PERIOD="2016" OBS_VALUE="33579283" OBS_STATUS="A" UNIT_MULT="0" NATURE="_X" TIME_DETAIL="2016" SOURCE_DETAIL="TIDES database"></Obs>
  </Series>
  <Series FREQ="A" REPORTING_TYPE="N" SERIES="_L_GH_140401_01" REF_AREA="GH" SEX="_T" AGE="_T" URBANISATION="_T" INCOME_WEALTH_QUANTILE="_T" EDUCATION_LEV="_T" OCCUPATION="_T" CUST_BREAKDOWN="_T" COMPOSITE_BREAKDOWN="_T" DISABILITY_STATUS="_T" ACTIVITY="_T" PRODUCT="_L_GH_ROUSAR" UNIT_MEASURE="CM">
    <Obs TIME_PERIOD="2020" OBS_VALUE="17.7" OBS_STATUS="A" UNIT_MULT="0" NATURE="_X" TIME_DETAIL="2020" SOURCE_DETAIL="Ministry of Fisheries and Aquaculture Development, 2021"></Obs>
  </Series>
  <Series FREQ="A" REPORTING_TYPE="N" SERIES="_L_GH_140401_01" REF_AREA="GH" SEX="_T" AGE="_T" URBANISATION="_T" INCOME_WEALTH_QUANTILE="_T" EDUCATION_LEV="_T" OCCUPATION="_T" CUST_BREAKDOWN="_T" COMPOSITE_BREAKDOWN="_T" DISABILITY_STATUS="_T" ACTIVITY="_T" PRODUCT="_L_GH_FLATSAR" UNIT_MEASURE="CM">
    <Obs TIME_PERIOD="2020" OBS_VALUE="16.2" OBS_STATUS="A" UNIT_MULT="0" NATURE="_X" TIME_DETAIL="2020" SOURCE_DETAIL="Ministry of Fisheries and Aquaculture Development, 2022"></Obs>
  </Series>
  <Series FREQ="A" REPORTING_TYPE="N" SERIES="_L_GH_140401_01" REF_AREA="GH" SEX="_T" AGE="_T" URBANISATION="_T" INCOME_WEALTH_QUANTILE="_T" EDUCATION_LEV="_T" OCCUPATION="_T" CUST_BREAKDOWN="_T" COMPOSITE_BREAKDOWN="_T" DISABILITY_STATUS="_T" ACTIVITY="_T" PRODUCT="_L_GH_CHUBMACK" UNIT_MEASURE="CM">
    <Obs TIME_PERIOD="2020" OBS_VALUE="20.2" OBS_STATUS="A" UNIT_MULT="0" NATURE="_X" TIME_DETAIL="2020" SOURCE_DETAIL="Ministry of Fisheries and Aquaculture Development, 2023"></Obs>
  </Series>
  <Series FREQ="A" REPORTING_TYPE="N" SERIES="_L_GH_140401_01" REF_AREA="GH" SEX="_T" AGE="_T" URBANISATION="_T" INCOME_WEALTH_QUANTILE="_T" EDUCATION_LEV="_T" OCCUPATION="_T" CUST_BREAKDOWN="_T" COMPOSITE_BREAKDOWN="_T" DISABILITY_STATUS="_T" ACTIVITY="_T" PRODUCT="_L_GH_EUROANC" UNIT_MEASURE="CM">
    <Obs TIME_PERIOD="2020" OBS_VALUE="9.1" OBS_STATUS="A" UNIT_MULT="0" NATURE="_X" TIME_DETAIL="2020" SOURCE_DETAIL="Ministry of Fisheries and Aquaculture Development, 2024"></Obs>
  </Series>
  <Series FREQ="A" REPORTING_TYPE="N" SERIES="_L_GH_140401_01" REF_AREA="GH" SEX="_T" AGE="_T" URBANISATION="_T" INCOME_WEALTH_QUANTILE="_T" EDUCATION_LEV="_T" OCCUPATION="_T" CUST_BREAKDOWN="_T" COMPOSITE_BREAKDOWN="_T" DISABILITY_STATUS="_T" ACTIVITY="_T" PRODUCT="_L_GH_BURRITTO" UNIT_MEASURE="CM">
    <Obs TIME_PERIOD="2020" OBS_VALUE="13.4" OBS_STATUS="A" UNIT_MULT="0" NATURE="_X" TIME_DETAIL="2020" SOURCE_DETAIL="Ministry of Fisheries and Aquaculture Development, 2025"></Obs>
  </Series>
  <Series FREQ="A" REPORTING_TYPE="N" SERIES="_L_GH_140401_01" REF_AREA="GH" SEX="_T" AGE="_T" URBANISATION="_T" INCOME_WEALTH_QUANTILE="_T" EDUCATION_LEV="_T" OCCUPATION="_T" CUST_BREAKDOWN="_T" COMPOSITE_BREAKDOWN="_T" DISABILITY_STATUS="_T" ACTIVITY="_T" PRODUCT="_L_GH_REDPAN" UNIT_MEASURE="CM">
    <Obs TIME_PERIOD="2020" OBS_VALUE="16.2" OBS_STATUS="A" UNIT_MULT="0" NATURE="_X" TIME_DETAIL="2020" SOURCE_DETAIL="Ministry of Fisheries and Aquaculture Development, 2026"></Obs>
  </Series>
  <Series FREQ="A" REPORTING_TYPE="N" SERIES="_L_GH_140401_01" REF_AREA="GH" SEX="_T" AGE="_T" URBANISATION="_T" INCOME_WEALTH_QUANTILE="_T" EDUCATION_LEV="_T" OCCUPATION="_T" CUST_BREAKDOWN="_T" COMPOSITE_BREAKDOWN="_T" DISABILITY_STATUS="_T" ACTIVITY="_T" PRODUCT="_L_GH_CASFISH" UNIT_MEASURE="CM">
    <Obs TIME_PERIOD="2020" OBS_VALUE="21.7" OBS_STATUS="A" UNIT_MULT="0" NATURE="_X" TIME_DETAIL="2020" SOURCE_DETAIL="Ministry of Fisheries and Aquaculture Development, 2027"></Obs>
  </Series>
  <Series FREQ="A" REPORTING_TYPE="N" SERIES="_L_GH_140401_01" REF_AREA="GH" SEX="_T" AGE="_T" URBANISATION="_T" INCOME_WEALTH_QUANTILE="_T" EDUCATION_LEV="_T" OCCUPATION="_T" CUST_BREAKDOWN="_T" COMPOSITE_BREAKDOWN="_T" DISABILITY_STATUS="_T" ACTIVITY="_T" PRODUCT="_L_GH_REDMUL" UNIT_MEASURE="CM">
    <Obs TIME_PERIOD="2020" OBS_VALUE="17.5" OBS_STATUS="A" UNIT_MULT="0" NATURE="_X" TIME_DETAIL="2020" SOURCE_DETAIL="Ministry of Fisheries and Aquaculture Development, 2028"></Obs>
  </Series>
  <Series FREQ="A" REPORTING_TYPE="N" SERIES="_L_GH_140401_01" REF_AREA="GH" SEX="_T" AGE="_T" URBANISATION="_T" INCOME_WEALTH_QUANTILE="_T" EDUCATION_LEV="_T" OCCUPATION="_T" CUST_BREAKDOWN="_T" COMPOSITE_BREAKDOWN="_T" DISABILITY_STATUS="_T" ACTIVITY="_T" PRODUCT="_L_GH_ANGDEN" UNIT_MEASURE="CM">
    <Obs TIME_PERIOD="2020" OBS_VALUE="20.3" OBS_STATUS="A" UNIT_MULT="0" NATURE="_X" TIME_DETAIL="2020" SOURCE_DETAIL="Ministry of Fisheries and Aquaculture Development, 2029"></Obs>
  </Series>
  <Series FREQ="A" REPORTING_TYPE="N" SERIES="_L_GH_140501_01" REF_AREA="GH" SEX="_T" AGE="_T" URBANISATION="_T" INCOME_WEALTH_QUANTILE="_T" EDUCATION_LEV="_T" OCCUPATION="_T" CUST_BREAKDOWN="_T" COMPOSITE_BREAKDOWN="_T" DISABILITY_STATUS="_T" ACTIVITY="_T" PRODUCT="_T" UNIT_MEASURE="IX">
    <Obs TIME_PERIOD="2016" OBS_VALUE="63.19" OBS_STATUS="A" UNIT_MULT="0" NATURE="_X" TIME_DETAIL="2016" SOURCE_DETAIL="Ocean Health Index (OHI), 2022"></Obs>
    <Obs TIME_PERIOD="2017" OBS_VALUE="63.74" OBS_STATUS="A" UNIT_MULT="0" NATURE="_X" TIME_DETAIL="2017" SOURCE_DETAIL="Ocean Health Index (OHI), 2022"></Obs>
    <Obs TIME_PERIOD="2018" OBS_VALUE="63.92" OBS_STATUS="A" UNIT_MULT="0" NATURE="_X" TIME_DETAIL="2018" SOURCE_DETAIL="Ocean Health Index (OHI), 2022"></Obs>
    <Obs TIME_PERIOD="2019" OBS_VALUE="63.44" OBS_STATUS="A" UNIT_MULT="0" NATURE="_X" TIME_DETAIL="2019" SOURCE_DETAIL="Ocean Health Index (OHI), 2022"></Obs>
    <Obs TIME_PERIOD="2020" OBS_VALUE="63.32" OBS_STATUS="A" UNIT_MULT="0" NATURE="_X" TIME_DETAIL="2020" SOURCE_DETAIL="Ocean Health Index (OHI), 2022"></Obs>
    <Obs TIME_PERIOD="2021" OBS_VALUE="63.26" OBS_STATUS="A" UNIT_MULT="0" NATURE="_X" TIME_DETAIL="2021" SOURCE_DETAIL="Ocean Health Index (OHI), 2022"></Obs>
  </Series>
  <Series FREQ="A" REPORTING_TYPE="N" SERIES="_L_GH_140501_02" REF_AREA="GH" SEX="_T" AGE="_T" URBANISATION="_T" INCOME_WEALTH_QUANTILE="_T" EDUCATION_LEV="_T" OCCUPATION="_T" CUST_BREAKDOWN="_T" COMPOSITE_BREAKDOWN="_T" DISABILITY_STATUS="_T" ACTIVITY="_T" PRODUCT="_T" UNIT_MEASURE="IX">
    <Obs TIME_PERIOD="2016" OBS_VALUE="50.11" OBS_STATUS="A" UNIT_MULT="0" NATURE="_X" TIME_DETAIL="2016" SOURCE_DETAIL="Ocean Health Index (OHI), 2022"></Obs>
    <Obs TIME_PERIOD="2017" OBS_VALUE="49.81" OBS_STATUS="A" UNIT_MULT="0" NATURE="_X" TIME_DETAIL="2017" SOURCE_DETAIL="Ocean Health Index (OHI), 2022"></Obs>
    <Obs TIME_PERIOD="2018" OBS_VALUE="49.27" OBS_STATUS="A" UNIT_MULT="0" NATURE="_X" TIME_DETAIL="2018" SOURCE_DETAIL="Ocean Health Index (OHI), 2022"></Obs>
    <Obs TIME_PERIOD="2019" OBS_VALUE="48.61" OBS_STATUS="A" UNIT_MULT="0" NATURE="_X" TIME_DETAIL="2019" SOURCE_DETAIL="Ocean Health Index (OHI), 2022"></Obs>
    <Obs TIME_PERIOD="2020" OBS_VALUE="47.71" OBS_STATUS="A" UNIT_MULT="0" NATURE="_X" TIME_DETAIL="2020" SOURCE_DETAIL="Ocean Health Index (OHI), 2022"></Obs>
    <Obs TIME_PERIOD="2021" OBS_VALUE="47.22" OBS_STATUS="A" UNIT_MULT="0" NATURE="_X" TIME_DETAIL="2021" SOURCE_DETAIL="Ocean Health Index (OHI), 2022"></Obs>
  </Series>
  <Series FREQ="A" REPORTING_TYPE="N" SERIES="_L_GH_140501_03" REF_AREA="GH" SEX="_T" AGE="_T" URBANISATION="_T" INCOME_WEALTH_QUANTILE="_T" EDUCATION_LEV="_T" OCCUPATION="_T" CUST_BREAKDOWN="_T" COMPOSITE_BREAKDOWN="_T" DISABILITY_STATUS="_T" ACTIVITY="_T" PRODUCT="_T" UNIT_MEASURE="IX">
    <Obs TIME_PERIOD="2016" OBS_VALUE="50.11" OBS_STATUS="A" UNIT_MULT="0" NATURE="_X" TIME_DETAIL="2016" SOURCE_DETAIL="Ocean Health Index (OHI), 2022"></Obs>
    <Obs TIME_PERIOD="2017" OBS_VALUE="49.82" OBS_STATUS="A" UNIT_MULT="0" NATURE="_X" TIME_DETAIL="2017" SOURCE_DETAIL="Ocean Health Index (OHI), 2022"></Obs>
    <Obs TIME_PERIOD="2018" OBS_VALUE="49.28" OBS_STATUS="A" UNIT_MULT="0" NATURE="_X" TIME_DETAIL="2018" SOURCE_DETAIL="Ocean Health Index (OHI), 2022"></Obs>
    <Obs TIME_PERIOD="2019" OBS_VALUE="48.61" OBS_STATUS="A" UNIT_MULT="0" NATURE="_X" TIME_DETAIL="2019" SOURCE_DETAIL="Ocean Health Index (OHI), 2022"></Obs>
    <Obs TIME_PERIOD="2020" OBS_VALUE="47.71" OBS_STATUS="A" UNIT_MULT="0" NATURE="_X" TIME_DETAIL="2020" SOURCE_DETAIL="Ocean Health Index (OHI), 2022"></Obs>
    <Obs TIME_PERIOD="2021" OBS_VALUE="47.22" OBS_STATUS="A" UNIT_MULT="0" NATURE="_X" TIME_DETAIL="2021" SOURCE_DETAIL="Ocean Health Index (OHI), 2022"></Obs>
  </Series>
  <Series FREQ="A" REPORTING_TYPE="N" SERIES="_L_GH_140501_04" REF_AREA="GH" SEX="_T" AGE="_T" URBANISATION="_T" INCOME_WEALTH_QUANTILE="_T" EDUCATION_LEV="_T" OCCUPATION="_T" CUST_BREAKDOWN="_T" COMPOSITE_BREAKDOWN="_T" DISABILITY_STATUS="_T" ACTIVITY="_T" PRODUCT="_T" UNIT_MEASURE="IX">
    <Obs TIME_PERIOD="2016" OBS_VALUE="0.01" OBS_STATUS="A" UNIT_MULT="0" NATURE="_X" TIME_DETAIL="2016" SOURCE_DETAIL="Ocean Health Index (OHI), 2022"></Obs>
    <Obs TIME_PERIOD="2017" OBS_VALUE="0.01" OBS_STATUS="A" UNIT_MULT="0" NATURE="_X" TIME_DETAIL="2017" SOURCE_DETAIL="Ocean Health Index (OHI), 2022"></Obs>
    <Obs TIME_PERIOD="2018" OBS_VALUE="0.01" OBS_STATUS="A" UNIT_MULT="0" NATURE="_X" TIME_DETAIL="2018" SOURCE_DETAIL="Ocean Health Index (OHI), 2022"></Obs>
    <Obs TIME_PERIOD="2019" OBS_VALUE="0.01" OBS_STATUS="A" UNIT_MULT="0" NATURE="_X" TIME_DETAIL="2019" SOURCE_DETAIL="Ocean Health Index (OHI), 2022"></Obs>
    <Obs TIME_PERIOD="2020" OBS_VALUE="0.01" OBS_STATUS="A" UNIT_MULT="0" NATURE="_X" TIME_DETAIL="2020" SOURCE_DETAIL="Ocean Health Index (OHI), 2022"></Obs>
    <Obs TIME_PERIOD="2021" OBS_VALUE="0.01" OBS_STATUS="A" UNIT_MULT="0" NATURE="_X" TIME_DETAIL="2021" SOURCE_DETAIL="Ocean Health Index (OHI), 2022"></Obs>
  </Series>
  <Series FREQ="A" REPORTING_TYPE="N" SERIES="_L_GH_140501_05" REF_AREA="GH" SEX="_T" AGE="_T" URBANISATION="_T" INCOME_WEALTH_QUANTILE="_T" EDUCATION_LEV="_T" OCCUPATION="_T" CUST_BREAKDOWN="_T" COMPOSITE_BREAKDOWN="_T" DISABILITY_STATUS="_T" ACTIVITY="_T" PRODUCT="_T" UNIT_MEASURE="IX">
    <Obs TIME_PERIOD="2016" OBS_VALUE="72.01" OBS_STATUS="A" UNIT_MULT="0" NATURE="_X" TIME_DETAIL="2016" SOURCE_DETAIL="Ocean Health Index (OHI), 2022"></Obs>
    <Obs TIME_PERIOD="2017" OBS_VALUE="71.12" OBS_STATUS="A" UNIT_MULT="0" NATURE="_X" TIME_DETAIL="2017" SOURCE_DETAIL="Ocean Health Index (OHI), 2022"></Obs>
    <Obs TIME_PERIOD="2018" OBS_VALUE="69.9" OBS_STATUS="A" UNIT_MULT="0" NATURE="_X" TIME_DETAIL="2018" SOURCE_DETAIL="Ocean Health Index (OHI), 2022"></Obs>
    <Obs TIME_PERIOD="2019" OBS_VALUE="69.05" OBS_STATUS="A" UNIT_MULT="0" NATURE="_X" TIME_DETAIL="2019" SOURCE_DETAIL="Ocean Health Index (OHI), 2022"></Obs>
    <Obs TIME_PERIOD="2020" OBS_VALUE="68.33" OBS_STATUS="A" UNIT_MULT="0" NATURE="_X" TIME_DETAIL="2020" SOURCE_DETAIL="Ocean Health Index (OHI), 2022"></Obs>
    <Obs TIME_PERIOD="2021" OBS_VALUE="67.95" OBS_STATUS="A" UNIT_MULT="0" NATURE="_X" TIME_DETAIL="2021" SOURCE_DETAIL="Ocean Health Index (OHI), 2022"></Obs>
  </Series>
  <Series FREQ="A" REPORTING_TYPE="N" SERIES="_L_GH_140501_06" REF_AREA="GH" SEX="_T" AGE="_T" URBANISATION="_T" INCOME_WEALTH_QUANTILE="_T" EDUCATION_LEV="_T" OCCUPATION="_T" CUST_BREAKDOWN="_T" COMPOSITE_BREAKDOWN="_T" DISABILITY_STATUS="_T" ACTIVITY="_T" PRODUCT="_T" UNIT_MEASURE="IX">
    <Obs TIME_PERIOD="2016" OBS_VALUE="55.93" OBS_STATUS="A" UNIT_MULT="0" NATURE="_X" TIME_DETAIL="2016" SOURCE_DETAIL="Ocean Health Index (OHI), 2022"></Obs>
    <Obs TIME_PERIOD="2017" OBS_VALUE="62.57" OBS_STATUS="A" UNIT_MULT="0" NATURE="_X" TIME_DETAIL="2017" SOURCE_DETAIL="Ocean Health Index (OHI), 2022"></Obs>
    <Obs TIME_PERIOD="2018" OBS_VALUE="66.79" OBS_STATUS="A" UNIT_MULT="0" NATURE="_X" TIME_DETAIL="2018" SOURCE_DETAIL="Ocean Health Index (OHI), 2022"></Obs>
    <Obs TIME_PERIOD="2019" OBS_VALUE="68.11" OBS_STATUS="A" UNIT_MULT="0" NATURE="_X" TIME_DETAIL="2019" SOURCE_DETAIL="Ocean Health Index (OHI), 2022"></Obs>
    <Obs TIME_PERIOD="2020" OBS_VALUE="68.48" OBS_STATUS="A" UNIT_MULT="0" NATURE="_X" TIME_DETAIL="2020" SOURCE_DETAIL="Ocean Health Index (OHI), 2022"></Obs>
    <Obs TIME_PERIOD="2021" OBS_VALUE="69.01" OBS_STATUS="A" UNIT_MULT="0" NATURE="_X" TIME_DETAIL="2021" SOURCE_DETAIL="Ocean Health Index (OHI), 2022"></Obs>
  </Series>
  <Series FREQ="A" REPORTING_TYPE="N" SERIES="_L_GH_140501_07" REF_AREA="GH" SEX="_T" AGE="_T" URBANISATION="_T" INCOME_WEALTH_QUANTILE="_T" EDUCATION_LEV="_T" OCCUPATION="_T" CUST_BREAKDOWN="_T" COMPOSITE_BREAKDOWN="_T" DISABILITY_STATUS="_T" ACTIVITY="_T" PRODUCT="_T" UNIT_MEASURE="IX">
    <Obs TIME_PERIOD="2016" OBS_VALUE="99.09" OBS_STATUS="A" UNIT_MULT="0" NATURE="_X" TIME_DETAIL="2016" SOURCE_DETAIL="Ocean Health Index (OHI), 2022"></Obs>
    <Obs TIME_PERIOD="2017" OBS_VALUE="99.09" OBS_STATUS="A" UNIT_MULT="0" NATURE="_X" TIME_DETAIL="2017" SOURCE_DETAIL="Ocean Health Index (OHI), 2022"></Obs>
    <Obs TIME_PERIOD="2018" OBS_VALUE="99.09" OBS_STATUS="A" UNIT_MULT="0" NATURE="_X" TIME_DETAIL="2018" SOURCE_DETAIL="Ocean Health Index (OHI), 2022"></Obs>
    <Obs TIME_PERIOD="2019" OBS_VALUE="99.09" OBS_STATUS="A" UNIT_MULT="0" NATURE="_X" TIME_DETAIL="2019" SOURCE_DETAIL="Ocean Health Index (OHI), 2022"></Obs>
    <Obs TIME_PERIOD="2020" OBS_VALUE="99.09" OBS_STATUS="A" UNIT_MULT="0" NATURE="_X" TIME_DETAIL="2020" SOURCE_DETAIL="Ocean Health Index (OHI), 2022"></Obs>
    <Obs TIME_PERIOD="2021" OBS_VALUE="99.09" OBS_STATUS="A" UNIT_MULT="0" NATURE="_X" TIME_DETAIL="2021" SOURCE_DETAIL="Ocean Health Index (OHI), 2022"></Obs>
  </Series>
  <Series FREQ="A" REPORTING_TYPE="N" SERIES="_L_GH_140501_08" REF_AREA="GH" SEX="_T" AGE="_T" URBANISATION="_T" INCOME_WEALTH_QUANTILE="_T" EDUCATION_LEV="_T" OCCUPATION="_T" CUST_BREAKDOWN="_T" COMPOSITE_BREAKDOWN="_T" DISABILITY_STATUS="_T" ACTIVITY="_T" PRODUCT="_T" UNIT_MEASURE="IX">
    <Obs TIME_PERIOD="2016" OBS_VALUE="98" OBS_STATUS="A" UNIT_MULT="0" NATURE="_X" TIME_DETAIL="2016" SOURCE_DETAIL="Ocean Health Index (OHI), 2022"></Obs>
    <Obs TIME_PERIOD="2017" OBS_VALUE="98" OBS_STATUS="A" UNIT_MULT="0" NATURE="_X" TIME_DETAIL="2017" SOURCE_DETAIL="Ocean Health Index (OHI), 2022"></Obs>
    <Obs TIME_PERIOD="2018" OBS_VALUE="98" OBS_STATUS="A" UNIT_MULT="0" NATURE="_X" TIME_DETAIL="2018" SOURCE_DETAIL="Ocean Health Index (OHI), 2022"></Obs>
    <Obs TIME_PERIOD="2019" OBS_VALUE="98" OBS_STATUS="A" UNIT_MULT="0" NATURE="_X" TIME_DETAIL="2019" SOURCE_DETAIL="Ocean Health Index (OHI), 2022"></Obs>
    <Obs TIME_PERIOD="2020" OBS_VALUE="98" OBS_STATUS="A" UNIT_MULT="0" NATURE="_X" TIME_DETAIL="2020" SOURCE_DETAIL="Ocean Health Index (OHI), 2022"></Obs>
    <Obs TIME_PERIOD="2021" OBS_VALUE="98" OBS_STATUS="A" UNIT_MULT="0" NATURE="_X" TIME_DETAIL="2021" SOURCE_DETAIL="Ocean Health Index (OHI), 2022"></Obs>
  </Series>
  <Series FREQ="A" REPORTING_TYPE="N" SERIES="_L_GH_140501_09" REF_AREA="GH" SEX="_T" AGE="_T" URBANISATION="_T" INCOME_WEALTH_QUANTILE="_T" EDUCATION_LEV="_T" OCCUPATION="_T" CUST_BREAKDOWN="_T" COMPOSITE_BREAKDOWN="_T" DISABILITY_STATUS="_T" ACTIVITY="_T" PRODUCT="_T" UNIT_MEASURE="IX">
    <Obs TIME_PERIOD="2016" OBS_VALUE="93.84" OBS_STATUS="A" UNIT_MULT="0" NATURE="_X" TIME_DETAIL="2016" SOURCE_DETAIL="Ocean Health Index (OHI), 2022"></Obs>
    <Obs TIME_PERIOD="2017" OBS_VALUE="93.84" OBS_STATUS="A" UNIT_MULT="0" NATURE="_X" TIME_DETAIL="2017" SOURCE_DETAIL="Ocean Health Index (OHI), 2022"></Obs>
    <Obs TIME_PERIOD="2018" OBS_VALUE="93.84" OBS_STATUS="A" UNIT_MULT="0" NATURE="_X" TIME_DETAIL="2018" SOURCE_DETAIL="Ocean Health Index (OHI), 2022"></Obs>
    <Obs TIME_PERIOD="2019" OBS_VALUE="93.84" OBS_STATUS="A" UNIT_MULT="0" NATURE="_X" TIME_DETAIL="2019" SOURCE_DETAIL="Ocean Health Index (OHI), 2022"></Obs>
    <Obs TIME_PERIOD="2020" OBS_VALUE="93.84" OBS_STATUS="A" UNIT_MULT="0" NATURE="_X" TIME_DETAIL="2020" SOURCE_DETAIL="Ocean Health Index (OHI), 2022"></Obs>
    <Obs TIME_PERIOD="2021" OBS_VALUE="93.84" OBS_STATUS="A" UNIT_MULT="0" NATURE="_X" TIME_DETAIL="2021" SOURCE_DETAIL="Ocean Health Index (OHI), 2022"></Obs>
  </Series>
  <Series FREQ="A" REPORTING_TYPE="N" SERIES="_L_GH_140501_10" REF_AREA="GH" SEX="_T" AGE="_T" URBANISATION="_T" INCOME_WEALTH_QUANTILE="_T" EDUCATION_LEV="_T" OCCUPATION="_T" CUST_BREAKDOWN="_T" COMPOSITE_BREAKDOWN="_T" DISABILITY_STATUS="_T" ACTIVITY="_T" PRODUCT="_T" UNIT_MEASURE="IX">
    <Obs TIME_PERIOD="2016" OBS_VALUE="89.35" OBS_STATUS="A" UNIT_MULT="0" NATURE="_X" TIME_DETAIL="2016" SOURCE_DETAIL="Ocean Health Index (OHI), 2022"></Obs>
    <Obs TIME_PERIOD="2017" OBS_VALUE="89.35" OBS_STATUS="A" UNIT_MULT="0" NATURE="_X" TIME_DETAIL="2017" SOURCE_DETAIL="Ocean Health Index (OHI), 2022"></Obs>
    <Obs TIME_PERIOD="2018" OBS_VALUE="89.35" OBS_STATUS="A" UNIT_MULT="0" NATURE="_X" TIME_DETAIL="2018" SOURCE_DETAIL="Ocean Health Index (OHI), 2022"></Obs>
    <Obs TIME_PERIOD="2019" OBS_VALUE="89.35" OBS_STATUS="A" UNIT_MULT="0" NATURE="_X" TIME_DETAIL="2019" SOURCE_DETAIL="Ocean Health Index (OHI), 2022"></Obs>
    <Obs TIME_PERIOD="2020" OBS_VALUE="89.35" OBS_STATUS="A" UNIT_MULT="0" NATURE="_X" TIME_DETAIL="2020" SOURCE_DETAIL="Ocean Health Index (OHI), 2022"></Obs>
    <Obs TIME_PERIOD="2021" OBS_VALUE="89.35" OBS_STATUS="A" UNIT_MULT="0" NATURE="_X" TIME_DETAIL="2021" SOURCE_DETAIL="Ocean Health Index (OHI), 2022"></Obs>
  </Series>
  <Series FREQ="A" REPORTING_TYPE="N" SERIES="_L_GH_140501_11" REF_AREA="GH" SEX="_T" AGE="_T" URBANISATION="_T" INCOME_WEALTH_QUANTILE="_T" EDUCATION_LEV="_T" OCCUPATION="_T" CUST_BREAKDOWN="_T" COMPOSITE_BREAKDOWN="_T" DISABILITY_STATUS="_T" ACTIVITY="_T" PRODUCT="_T" UNIT_MEASURE="IX">
    <Obs TIME_PERIOD="2016" OBS_VALUE="98.32" OBS_STATUS="A" UNIT_MULT="0" NATURE="_X" TIME_DETAIL="2016" SOURCE_DETAIL="Ocean Health Index (OHI), 2022"></Obs>
    <Obs TIME_PERIOD="2017" OBS_VALUE="98.32" OBS_STATUS="A" UNIT_MULT="0" NATURE="_X" TIME_DETAIL="2017" SOURCE_DETAIL="Ocean Health Index (OHI), 2022"></Obs>
    <Obs TIME_PERIOD="2018" OBS_VALUE="98.32" OBS_STATUS="A" UNIT_MULT="0" NATURE="_X" TIME_DETAIL="2018" SOURCE_DETAIL="Ocean Health Index (OHI), 2022"></Obs>
    <Obs TIME_PERIOD="2019" OBS_VALUE="98.32" OBS_STATUS="A" UNIT_MULT="0" NATURE="_X" TIME_DETAIL="2019" SOURCE_DETAIL="Ocean Health Index (OHI), 2022"></Obs>
    <Obs TIME_PERIOD="2020" OBS_VALUE="98.32" OBS_STATUS="A" UNIT_MULT="0" NATURE="_X" TIME_DETAIL="2020" SOURCE_DETAIL="Ocean Health Index (OHI), 2022"></Obs>
    <Obs TIME_PERIOD="2021" OBS_VALUE="98.32" OBS_STATUS="A" UNIT_MULT="0" NATURE="_X" TIME_DETAIL="2021" SOURCE_DETAIL="Ocean Health Index (OHI), 2022"></Obs>
  </Series>
  <Series FREQ="A" REPORTING_TYPE="N" SERIES="_L_GH_140501_12" REF_AREA="GH" SEX="_T" AGE="_T" URBANISATION="_T" INCOME_WEALTH_QUANTILE="_T" EDUCATION_LEV="_T" OCCUPATION="_T" CUST_BREAKDOWN="_T" COMPOSITE_BREAKDOWN="_T" DISABILITY_STATUS="_T" ACTIVITY="_T" PRODUCT="_T" UNIT_MEASURE="IX">
    <Obs TIME_PERIOD="2016" OBS_VALUE="10.65" OBS_STATUS="A" UNIT_MULT="0" NATURE="_X" TIME_DETAIL="2016" SOURCE_DETAIL="Ocean Health Index (OHI), 2022"></Obs>
    <Obs TIME_PERIOD="2017" OBS_VALUE="11.12" OBS_STATUS="A" UNIT_MULT="0" NATURE="_X" TIME_DETAIL="2017" SOURCE_DETAIL="Ocean Health Index (OHI), 2022"></Obs>
    <Obs TIME_PERIOD="2018" OBS_VALUE="11.15" OBS_STATUS="A" UNIT_MULT="0" NATURE="_X" TIME_DETAIL="2018" SOURCE_DETAIL="Ocean Health Index (OHI), 2022"></Obs>
    <Obs TIME_PERIOD="2019" OBS_VALUE="11.35" OBS_STATUS="A" UNIT_MULT="0" NATURE="_X" TIME_DETAIL="2019" SOURCE_DETAIL="Ocean Health Index (OHI), 2022"></Obs>
    <Obs TIME_PERIOD="2020" OBS_VALUE="11.6" OBS_STATUS="A" UNIT_MULT="0" NATURE="_X" TIME_DETAIL="2020" SOURCE_DETAIL="Ocean Health Index (OHI), 2022"></Obs>
    <Obs TIME_PERIOD="2021" OBS_VALUE="11.58" OBS_STATUS="A" UNIT_MULT="0" NATURE="_X" TIME_DETAIL="2021" SOURCE_DETAIL="Ocean Health Index (OHI), 2022"></Obs>
  </Series>
  <Series FREQ="A" REPORTING_TYPE="N" SERIES="_L_GH_140501_13" REF_AREA="GH" SEX="_T" AGE="_T" URBANISATION="_T" INCOME_WEALTH_QUANTILE="_T" EDUCATION_LEV="_T" OCCUPATION="_T" CUST_BREAKDOWN="_T" COMPOSITE_BREAKDOWN="_T" DISABILITY_STATUS="_T" ACTIVITY="_T" PRODUCT="_T" UNIT_MEASURE="IX">
    <Obs TIME_PERIOD="2016" OBS_VALUE="35.46" OBS_STATUS="A" UNIT_MULT="0" NATURE="_X" TIME_DETAIL="2016" SOURCE_DETAIL="Ocean Health Index (OHI), 2022"></Obs>
    <Obs TIME_PERIOD="2017" OBS_VALUE="35.44" OBS_STATUS="A" UNIT_MULT="0" NATURE="_X" TIME_DETAIL="2017" SOURCE_DETAIL="Ocean Health Index (OHI), 2022"></Obs>
    <Obs TIME_PERIOD="2018" OBS_VALUE="35.42" OBS_STATUS="A" UNIT_MULT="0" NATURE="_X" TIME_DETAIL="2018" SOURCE_DETAIL="Ocean Health Index (OHI), 2022"></Obs>
    <Obs TIME_PERIOD="2019" OBS_VALUE="32.25" OBS_STATUS="A" UNIT_MULT="0" NATURE="_X" TIME_DETAIL="2019" SOURCE_DETAIL="Ocean Health Index (OHI), 2022"></Obs>
    <Obs TIME_PERIOD="2020" OBS_VALUE="32.18" OBS_STATUS="A" UNIT_MULT="0" NATURE="_X" TIME_DETAIL="2020" SOURCE_DETAIL="Ocean Health Index (OHI), 2022"></Obs>
    <Obs TIME_PERIOD="2021" OBS_VALUE="32.11" OBS_STATUS="A" UNIT_MULT="0" NATURE="_X" TIME_DETAIL="2021" SOURCE_DETAIL="Ocean Health Index (OHI), 2022"></Obs>
  </Series>
  <Series FREQ="A" REPORTING_TYPE="N" SERIES="_L_GH_140501_14" REF_AREA="GH" SEX="_T" AGE="_T" URBANISATION="_T" INCOME_WEALTH_QUANTILE="_T" EDUCATION_LEV="_T" OCCUPATION="_T" CUST_BREAKDOWN="_T" COMPOSITE_BREAKDOWN="_T" DISABILITY_STATUS="_T" ACTIVITY="_T" PRODUCT="_T" UNIT_MEASURE="IX">
    <Obs TIME_PERIOD="2016" OBS_VALUE="68.18" OBS_STATUS="A" UNIT_MULT="0" NATURE="_X" TIME_DETAIL="2016" SOURCE_DETAIL="Ocean Health Index (OHI), 2022"></Obs>
    <Obs TIME_PERIOD="2017" OBS_VALUE="68.14" OBS_STATUS="A" UNIT_MULT="0" NATURE="_X" TIME_DETAIL="2017" SOURCE_DETAIL="Ocean Health Index (OHI), 2022"></Obs>
    <Obs TIME_PERIOD="2018" OBS_VALUE="68.1" OBS_STATUS="A" UNIT_MULT="0" NATURE="_X" TIME_DETAIL="2018" SOURCE_DETAIL="Ocean Health Index (OHI), 2022"></Obs>
    <Obs TIME_PERIOD="2019" OBS_VALUE="61.76" OBS_STATUS="A" UNIT_MULT="0" NATURE="_X" TIME_DETAIL="2019" SOURCE_DETAIL="Ocean Health Index (OHI), 2022"></Obs>
    <Obs TIME_PERIOD="2020" OBS_VALUE="61.63" OBS_STATUS="A" UNIT_MULT="0" NATURE="_X" TIME_DETAIL="2020" SOURCE_DETAIL="Ocean Health Index (OHI), 2022"></Obs>
    <Obs TIME_PERIOD="2021" OBS_VALUE="61.49" OBS_STATUS="A" UNIT_MULT="0" NATURE="_X" TIME_DETAIL="2021" SOURCE_DETAIL="Ocean Health Index (OHI), 2022"></Obs>
  </Series>
  <Series FREQ="A" REPORTING_TYPE="N" SERIES="_L_GH_140501_15" REF_AREA="GH" SEX="_T" AGE="_T" URBANISATION="_T" INCOME_WEALTH_QUANTILE="_T" EDUCATION_LEV="_T" OCCUPATION="_T" CUST_BREAKDOWN="_T" COMPOSITE_BREAKDOWN="_T" DISABILITY_STATUS="_T" ACTIVITY="_T" PRODUCT="_T" UNIT_MEASURE="IX">
    <Obs TIME_PERIOD="2016" OBS_VALUE="2.73" OBS_STATUS="A" UNIT_MULT="0" NATURE="_X" TIME_DETAIL="2016" SOURCE_DETAIL="Ocean Health Index (OHI), 2022"></Obs>
    <Obs TIME_PERIOD="2017" OBS_VALUE="2.73" OBS_STATUS="A" UNIT_MULT="0" NATURE="_X" TIME_DETAIL="2017" SOURCE_DETAIL="Ocean Health Index (OHI), 2022"></Obs>
    <Obs TIME_PERIOD="2018" OBS_VALUE="2.73" OBS_STATUS="A" UNIT_MULT="0" NATURE="_X" TIME_DETAIL="2018" SOURCE_DETAIL="Ocean Health Index (OHI), 2022"></Obs>
    <Obs TIME_PERIOD="2019" OBS_VALUE="2.73" OBS_STATUS="A" UNIT_MULT="0" NATURE="_X" TIME_DETAIL="2019" SOURCE_DETAIL="Ocean Health Index (OHI), 2022"></Obs>
    <Obs TIME_PERIOD="2020" OBS_VALUE="2.73" OBS_STATUS="A" UNIT_MULT="0" NATURE="_X" TIME_DETAIL="2020" SOURCE_DETAIL="Ocean Health Index (OHI), 2022"></Obs>
    <Obs TIME_PERIOD="2021" OBS_VALUE="2.73" OBS_STATUS="A" UNIT_MULT="0" NATURE="_X" TIME_DETAIL="2021" SOURCE_DETAIL="Ocean Health Index (OHI), 2022"></Obs>
  </Series>
  <Series FREQ="A" REPORTING_TYPE="N" SERIES="_L_GH_140501_16" REF_AREA="GH" SEX="_T" AGE="_T" URBANISATION="_T" INCOME_WEALTH_QUANTILE="_T" EDUCATION_LEV="_T" OCCUPATION="_T" CUST_BREAKDOWN="_T" COMPOSITE_BREAKDOWN="_T" DISABILITY_STATUS="_T" ACTIVITY="_T" PRODUCT="_T" UNIT_MEASURE="IX">
    <Obs TIME_PERIOD="2016" OBS_VALUE="35.55" OBS_STATUS="A" UNIT_MULT="0" NATURE="_X" TIME_DETAIL="2016" SOURCE_DETAIL="Ocean Health Index (OHI), 2022"></Obs>
    <Obs TIME_PERIOD="2017" OBS_VALUE="35.25" OBS_STATUS="A" UNIT_MULT="0" NATURE="_X" TIME_DETAIL="2017" SOURCE_DETAIL="Ocean Health Index (OHI), 2022"></Obs>
    <Obs TIME_PERIOD="2018" OBS_VALUE="35.25" OBS_STATUS="A" UNIT_MULT="0" NATURE="_X" TIME_DETAIL="2018" SOURCE_DETAIL="Ocean Health Index (OHI), 2022"></Obs>
    <Obs TIME_PERIOD="2019" OBS_VALUE="33.61" OBS_STATUS="A" UNIT_MULT="0" NATURE="_X" TIME_DETAIL="2019" SOURCE_DETAIL="Ocean Health Index (OHI), 2022"></Obs>
    <Obs TIME_PERIOD="2020" OBS_VALUE="33.49" OBS_STATUS="A" UNIT_MULT="0" NATURE="_X" TIME_DETAIL="2020" SOURCE_DETAIL="Ocean Health Index (OHI), 2022"></Obs>
    <Obs TIME_PERIOD="2021" OBS_VALUE="33.37" OBS_STATUS="A" UNIT_MULT="0" NATURE="_X" TIME_DETAIL="2021" SOURCE_DETAIL="Ocean Health Index (OHI), 2022"></Obs>
  </Series>
  <Series FREQ="A" REPORTING_TYPE="N" SERIES="_L_GH_140501_17" REF_AREA="GH" SEX="_T" AGE="_T" URBANISATION="_T" INCOME_WEALTH_QUANTILE="_T" EDUCATION_LEV="_T" OCCUPATION="_T" CUST_BREAKDOWN="_T" COMPOSITE_BREAKDOWN="_T" DISABILITY_STATUS="_T" ACTIVITY="_T" PRODUCT="_T" UNIT_MEASURE="IX">
    <Obs TIME_PERIOD="2016" OBS_VALUE="81.3" OBS_STATUS="A" UNIT_MULT="0" NATURE="_X" TIME_DETAIL="2016" SOURCE_DETAIL="Ocean Health Index (OHI), 2022"></Obs>
    <Obs TIME_PERIOD="2017" OBS_VALUE="81.14" OBS_STATUS="A" UNIT_MULT="0" NATURE="_X" TIME_DETAIL="2017" SOURCE_DETAIL="Ocean Health Index (OHI), 2022"></Obs>
    <Obs TIME_PERIOD="2018" OBS_VALUE="80.5" OBS_STATUS="A" UNIT_MULT="0" NATURE="_X" TIME_DETAIL="2018" SOURCE_DETAIL="Ocean Health Index (OHI), 2022"></Obs>
    <Obs TIME_PERIOD="2019" OBS_VALUE="80.49" OBS_STATUS="A" UNIT_MULT="0" NATURE="_X" TIME_DETAIL="2019" SOURCE_DETAIL="Ocean Health Index (OHI), 2022"></Obs>
    <Obs TIME_PERIOD="2020" OBS_VALUE="80.46" OBS_STATUS="A" UNIT_MULT="0" NATURE="_X" TIME_DETAIL="2020" SOURCE_DETAIL="Ocean Health Index (OHI), 2022"></Obs>
    <Obs TIME_PERIOD="2021" OBS_VALUE="80.46" OBS_STATUS="A" UNIT_MULT="0" NATURE="_X" TIME_DETAIL="2021" SOURCE_DETAIL="Ocean Health Index (OHI), 2022"></Obs>
  </Series>
  <Series FREQ="A" REPORTING_TYPE="N" SERIES="_L_GH_140501_18" REF_AREA="GH" SEX="_T" AGE="_T" URBANISATION="_T" INCOME_WEALTH_QUANTILE="_T" EDUCATION_LEV="_T" OCCUPATION="_T" CUST_BREAKDOWN="_T" COMPOSITE_BREAKDOWN="_T" DISABILITY_STATUS="_T" ACTIVITY="_T" PRODUCT="_T" UNIT_MEASURE="IX">
    <Obs TIME_PERIOD="2016" OBS_VALUE="87.85" OBS_STATUS="A" UNIT_MULT="0" NATURE="_X" TIME_DETAIL="2016" SOURCE_DETAIL="Ocean Health Index (OHI), 2022"></Obs>
    <Obs TIME_PERIOD="2017" OBS_VALUE="87.94" OBS_STATUS="A" UNIT_MULT="0" NATURE="_X" TIME_DETAIL="2017" SOURCE_DETAIL="Ocean Health Index (OHI), 2022"></Obs>
    <Obs TIME_PERIOD="2018" OBS_VALUE="87.08" OBS_STATUS="A" UNIT_MULT="0" NATURE="_X" TIME_DETAIL="2018" SOURCE_DETAIL="Ocean Health Index (OHI), 2022"></Obs>
    <Obs TIME_PERIOD="2019" OBS_VALUE="87.47" OBS_STATUS="A" UNIT_MULT="0" NATURE="_X" TIME_DETAIL="2019" SOURCE_DETAIL="Ocean Health Index (OHI), 2022"></Obs>
    <Obs TIME_PERIOD="2020" OBS_VALUE="87.85" OBS_STATUS="A" UNIT_MULT="0" NATURE="_X" TIME_DETAIL="2020" SOURCE_DETAIL="Ocean Health Index (OHI), 2022"></Obs>
    <Obs TIME_PERIOD="2021" OBS_VALUE="87.85" OBS_STATUS="A" UNIT_MULT="0" NATURE="_X" TIME_DETAIL="2021" SOURCE_DETAIL="Ocean Health Index (OHI), 2022"></Obs>
  </Series>
  <Series FREQ="A" REPORTING_TYPE="N" SERIES="_L_GH_140501_19" REF_AREA="GH" SEX="_T" AGE="_T" URBANISATION="_T" INCOME_WEALTH_QUANTILE="_T" EDUCATION_LEV="_T" OCCUPATION="_T" CUST_BREAKDOWN="_T" COMPOSITE_BREAKDOWN="_T" DISABILITY_STATUS="_T" ACTIVITY="_T" PRODUCT="_T" UNIT_MEASURE="IX">
    <Obs TIME_PERIOD="2016" OBS_VALUE="74.76" OBS_STATUS="A" UNIT_MULT="0" NATURE="_X" TIME_DETAIL="2016" SOURCE_DETAIL="Ocean Health Index (OHI), 2022"></Obs>
    <Obs TIME_PERIOD="2017" OBS_VALUE="74.34" OBS_STATUS="A" UNIT_MULT="0" NATURE="_X" TIME_DETAIL="2017" SOURCE_DETAIL="Ocean Health Index (OHI), 2022"></Obs>
    <Obs TIME_PERIOD="2018" OBS_VALUE="73.92" OBS_STATUS="A" UNIT_MULT="0" NATURE="_X" TIME_DETAIL="2018" SOURCE_DETAIL="Ocean Health Index (OHI), 2022"></Obs>
    <Obs TIME_PERIOD="2019" OBS_VALUE="73.5" OBS_STATUS="A" UNIT_MULT="0" NATURE="_X" TIME_DETAIL="2019" SOURCE_DETAIL="Ocean Health Index (OHI), 2022"></Obs>
    <Obs TIME_PERIOD="2020" OBS_VALUE="73.08" OBS_STATUS="A" UNIT_MULT="0" NATURE="_X" TIME_DETAIL="2020" SOURCE_DETAIL="Ocean Health Index (OHI), 2022"></Obs>
    <Obs TIME_PERIOD="2021" OBS_VALUE="73.08" OBS_STATUS="A" UNIT_MULT="0" NATURE="_X" TIME_DETAIL="2021" SOURCE_DETAIL="Ocean Health Index (OHI), 2022"></Obs>
  </Series>
  <Series FREQ="A" REPORTING_TYPE="N" SERIES="ER_REG_UNFCIM" REF_AREA="GH" SEX="_T" AGE="_T" URBANISATION="_T" INCOME_WEALTH_QUANTILE="_T" EDUCATION_LEV="_T" OCCUPATION="_T" CUST_BREAKDOWN="_T" COMPOSITE_BREAKDOWN="_T" DISABILITY_STATUS="_T" ACTIVITY="_T" PRODUCT="_T" UNIT_MEASURE="BAND">
    <Obs TIME_PERIOD="2018" OBS_VALUE="4" OBS_STATUS="A" UNIT_MULT="0" NATURE="_X" TIME_DETAIL="2018"></Obs>
    <Obs TIME_PERIOD="2022" OBS_VALUE="5" OBS_STATUS="A" UNIT_MULT="0" NATURE="_X" TIME_DETAIL="2022"></Obs>
  </Series>
</message:DataSet>
</message:StructureSpecificData>
